DiyiciDashanJiushangshou/README.md
DiyiciDashanJiushangshou/__init__.py
DiyiciDashanJiushangshou/__main__.py
DiyiciDashanJiushangshou/file.epub
DiyiciDashanJiushangshou/index.html
DiyiciDashanJiushangshou/css/__init__.py
DiyiciDashanJiushangshou/css/annotations.css
DiyiciDashanJiushangshou/css/main.css
DiyiciDashanJiushangshou/css/normalize.css
DiyiciDashanJiushangshou/css/popup.css
DiyiciDashanJiushangshou/font/__init__.py
DiyiciDashanJiushangshou/font/fontello.eot
DiyiciDashanJiushangshou/font/fontello.svg
DiyiciDashanJiushangshou/font/fontello.ttf
DiyiciDashanJiushangshou/font/fontello.woff
DiyiciDashanJiushangshou/img/__init__.py
DiyiciDashanJiushangshou/img/annotator-glyph-sprite.png
DiyiciDashanJiushangshou/img/annotator-icon-sprite.png
DiyiciDashanJiushangshou/img/apple-touch-icon.png
DiyiciDashanJiushangshou/img/cancelfullscreen.png
DiyiciDashanJiushangshou/img/close.png
DiyiciDashanJiushangshou/img/fullscreen.png
DiyiciDashanJiushangshou/img/loader.gif
DiyiciDashanJiushangshou/img/menu-icon.png
DiyiciDashanJiushangshou/img/save.png
DiyiciDashanJiushangshou/img/saved.png
DiyiciDashanJiushangshou/img/settings-s.png
DiyiciDashanJiushangshou/img/settings.png
DiyiciDashanJiushangshou/img/star.png
DiyiciDashanJiushangshou/js/__init__.py
DiyiciDashanJiushangshou/js/epub.js
DiyiciDashanJiushangshou/js/epub.min.js
DiyiciDashanJiushangshou/js/epub.min.map
DiyiciDashanJiushangshou/js/hooks.min.js
DiyiciDashanJiushangshou/js/hooks.min.map
DiyiciDashanJiushangshou/js/reader.js
DiyiciDashanJiushangshou/js/reader.js.map
DiyiciDashanJiushangshou/js/reader.min.js
DiyiciDashanJiushangshou/js/reader.min.map
DiyiciDashanJiushangshou/js/hooks/__init__.py
DiyiciDashanJiushangshou/js/hooks/extensions/__init__.py
DiyiciDashanJiushangshou/js/hooks/extensions/highlight.js
DiyiciDashanJiushangshou/js/libs/__init__.py
DiyiciDashanJiushangshou/js/libs/jquery.min.js
DiyiciDashanJiushangshou/js/libs/localforage.min.js
DiyiciDashanJiushangshou/js/libs/screenfull.js
diyici_dashan_jiushangshou-2022.10.11.0.dist-info/METADATA
diyici_dashan_jiushangshou-2022.10.11.0.dist-info/WHEEL
diyici_dashan_jiushangshou-2022.10.11.0.dist-info/entry_points.txt
diyici_dashan_jiushangshou-2022.10.11.0.dist-info/top_level.txt
diyici_dashan_jiushangshou-2022.10.11.0.dist-info/RECORD
